[
  {
    "model":"baseline1",
    "split":"random-5fold",
    "mae":42.5472621963,
    "rmse":54.5076861622,
    "mape":18.5716981608,
    "r2":0.1523687973
  },
  {
    "model":"baseline2",
    "split":"random-5fold",
    "mae":37.4458467367,
    "rmse":47.7564658122,
    "mape":16.2002500803,
    "r2":0.3493374645
  },
  {
    "model":"lgbm",
    "split":"random-5fold",
    "mae":33.4215346841,
    "rmse":43.4927228534,
    "mape":14.1495423716,
    "r2":0.4603345228
  },
  {
    "model":"baseline1",
    "split":"cold-city",
    "mae":43.2160840187,
    "rmse":55.2571460294,
    "mape":18.6795005898,
    "r2":0.1326912495
  },
  {
    "model":"baseline2",
    "split":"cold-city",
    "mae":41.4291151702,
    "rmse":52.8844736948,
    "mape":17.482065191,
    "r2":0.2055744547
  },
  {
    "model":"lgbm",
    "split":"cold-city",
    "mae":81.127654024,
    "rmse":98.7751481714,
    "mape":29.8146797129,
    "r2":-1.7713552957
  }
]